CHANGELOG.md
CREDITS.md
LICENSE.txt
MANIFEST.in
README.md
setup.py
PyHQ/__init__.py
PyHQ.egg-info/PKG-INFO
PyHQ.egg-info/SOURCES.txt
PyHQ.egg-info/dependency_links.txt
PyHQ.egg-info/requires.txt
PyHQ.egg-info/top_level.txt
PyHQ/English/Dictionary.py
PyHQ/English/__init__.py
PyHQ/Files/FileProperties.py
PyHQ/Files/__init__.py
PyHQ/Fun/Guesser.py
PyHQ/Fun/__init__.py
PyHQ/Math/Statistics.py
PyHQ/Math/Trigonometry.py
PyHQ/Math/__init__.py
PyHQ/Speech/TextToSpeech.py
PyHQ/Speech/__init__.py
PyHQ/System/Brightness.py
PyHQ/System/Clipboard.py
PyHQ/System/Volume.py
PyHQ/System/__init__.py
PyHQ/System/assets/SetVol.exe
PyHQ/UI/MessageBox.py
PyHQ/UI/__init__.py